python_sdk_client/__init__.py
python_sdk_client/clients_enum.py
python_sdk_client/cropin_api.py
python_sdk_client/libs/__init__.py
python_sdk_client/libs/abstract_client.py
python_sdk_client/libs/batch_processor.py
python_sdk_client/libs/client_cfg.py
python_sdk_client/libs/cropin_client.py
python_sdk_client/libs/cropin_exceptions.py
python_sdk_client/libs/insight_service_client.py
python_sdk_client/libs/keycloak_client.py
tests/__init__.py
tests/cropin_api_test.py
insights_sdk-0.0.6.dist-info/METADATA
insights_sdk-0.0.6.dist-info/WHEEL
insights_sdk-0.0.6.dist-info/top_level.txt
insights_sdk-0.0.6.dist-info/RECORD
