Metadata-Version: 2.1
Name: insights-sdk
Version: 0.0.6
Summary: Insights Service API
Home-page: 
Author-email: 
Keywords: Swagger,Insights Service API -test
Requires-Dist: urllib3 (>=1.15)
Requires-Dist: six (>=1.10)
Requires-Dist: certifi
Requires-Dist: python-dateutil
Requires-Dist: insights-python-client (>=0.0.2)
